mlcbakery/api/__init__.py
mlcbakery/api/access_level.py
mlcbakery/api/dependencies.py
mlcbakery/api/endpoints/activities.py
mlcbakery/api/endpoints/agents.py
mlcbakery/api/endpoints/api_keys.py
mlcbakery/api/endpoints/collections.py
mlcbakery/api/endpoints/datasets.py
mlcbakery/api/endpoints/entity_relationships.py
mlcbakery/api/endpoints/storage.py
mlcbakery/api/endpoints/task_details.py
mlcbakery/api/endpoints/tasks.py
mlcbakery/api/endpoints/trained_models.py
mlcbakery/auth/admin_token_strategy.py
mlcbakery/auth/jwks_strategy.py
mlcbakery/auth/jwt_strategy.py
mlcbakery/auth/passthrough_strategy.py
mlcbakery/bakery_client.py
mlcbakery/croissant_validation.py
mlcbakery/database.py
mlcbakery/main.py
mlcbakery/mcp/README.md
mlcbakery/mcp/main.py
mlcbakery/mcp/templates/download_dataset.huggingface.md
mlcbakery/mcp/templates/download_dataset.kaggle.md
mlcbakery/mcp/templates/download_dataset.openml.md
mlcbakery/mcp/templates/download_dataset.other.md
mlcbakery/mcp/templates/help.md
mlcbakery/mcp/tools.py
mlcbakery/metrics.py
mlcbakery/models.py
mlcbakery/schemas/activity.py
mlcbakery/schemas/agent.py
mlcbakery/schemas/api_key.py
mlcbakery/schemas/collection.py
mlcbakery/schemas/dataset.py
mlcbakery/schemas/entity.py
mlcbakery/schemas/entity_relationship.py
mlcbakery/schemas/storage.py
mlcbakery/schemas/task.py
mlcbakery/schemas/trained_model.py
mlcbakery/search.py
mlcbakery/storage/__init__.py
mlcbakery/storage/gcp.py
mlcbakery/version_manager.py
mlcbakery-0.1.6.dist-info/LICENSE
mlcbakery-0.1.6.dist-info/METADATA
mlcbakery-0.1.6.dist-info/WHEEL
mlcbakery-0.1.6.dist-info/entry_points.txt
mlcbakery-0.1.6.dist-info/RECORD
