Metadata-Version: 2.3
Name: mlcbakery
Version: 0.1.6
Summary: A machine learning data and model management system with provenance tracking
Author: Jonathan Lebensold
Author-email: jon@jetty.io
Requires-Python: >=3.12
Classifier: Programming Language :: Python :: 3
Classifier: Programming Language :: Python :: 3.12
Classifier: Programming Language :: Python :: 3.13
Requires-Dist: aiosqlite (>=0.21.0)
Requires-Dist: alembic (>=1.15.2)
Requires-Dist: asyncpg (>=0.30.0)
Requires-Dist: dotenv (>=0.9.9)
Requires-Dist: fastapi (>=0.115.12)
Requires-Dist: func-timeout (>=4.3.5)
Requires-Dist: google (>=3.0.0)
Requires-Dist: google-cloud-storage (>=3.1.0)
Requires-Dist: greenlet (>=3.2.1)
Requires-Dist: httpx (>=0.28.1)
Requires-Dist: mlcroissant (>=1.0.17)
Requires-Dist: opentelemetry-exporter-gcp-monitoring (>=1.9.0a0)
Requires-Dist: opentelemetry-exporter-gcp-trace (>=1.9.0)
Requires-Dist: opentelemetry-exporter-otlp (>=1.33.1)
Requires-Dist: opentelemetry-instrumentation-fastapi (>=0.54b1)
Requires-Dist: pandas (>=2.2.3)
Requires-Dist: poetry (>=2.1.3)
Requires-Dist: pyarrow (>=19.0.1)
Requires-Dist: pyjwt[crypto] (>=2.10.1)
Requires-Dist: pytest (>=8.3.5)
Requires-Dist: pytest-asyncio (>=0.26.0)
Requires-Dist: pytest-mock (>=3.10.0)
Requires-Dist: python-multipart (>=0.0.20)
Requires-Dist: requests (>=2.32.3)
Requires-Dist: sqlalchemy (>=2.0.40)
Requires-Dist: sqlalchemy-continuum (>=1.4.2)
Requires-Dist: starlette (>=0.46.2)
Requires-Dist: typesense (>=1.0.3)
Requires-Dist: uvicorn (>=0.34.2)
